AUTHORS
CHANGELOG.md
CONTRIBUTING.md
LICENSE.txt
MAINTAINERS.md
MANIFEST.in
README.md
setup.py
bin/hemlock-rest
docs/REST.md
docs/images/logo.png
hemlock_rest/__init__.py
hemlock_rest/hemlock_rest.py
hemlock_rest/test_hemlock_rest.py
hemlock_rest.egg-info/PKG-INFO
hemlock_rest.egg-info/SOURCES.txt
hemlock_rest.egg-info/dependency_links.txt
hemlock_rest.egg-info/requires.txt
hemlock_rest.egg-info/top_level.txt
hemlock_rest/static/favicon.ico
scripts/ci/setup_env_hemlock_rest.sh