Metadata-Version: 1.1
Name: hemlock-rest
Version: 0.1.1
Summary: Hemlock is a way of providing a common data access layer. This is a RESTful server for Hemlock.
Home-page: http://lab41.github.io/Hemlock-REST
Author: Charlie Lewis
Author-email: charliel@lab41.org
License: LICENSE.txt
Keywords: hemlock,metadata,cache,heterogeneous,restful,api
Platform: UNKNOWN
Classifier: Programming Language :: Python
Classifier: Operating System :: POSIX :: Linux
Classifier: Topic :: Software Development :: Libraries :: Application Frameworks
Classifier: Environment :: Other Environment
